{
  "parent": "minecraft:recipes/root",
  "rewards": {
    "recipes": [
      "oldguns:medium_grade_black_powder_block_vanilla"
    ]
  },
  "criteria": {
    "has_medium_grade_black_powder": {
      "trigger": "minecraft:inventory_changed",
      "conditions": {
        "items": [
          {
            "item": "oldguns:medium_grade_black_powder"
          }
        ]
      }
    },
    "has_the_recipe": {
      "trigger": "minecraft:recipe_unlocked",
      "conditions": {
        "recipe": "oldguns:medium_grade_black_powder_block_vanilla"
      }
    }
  },
  "requirements": [
    [
      "has_medium_grade_black_powder",
      "has_the_recipe"
    ]
  ]
}