{
  "parent": "minecraft:recipes/root",
  "criteria": {
    "has_charcoal": {
      "conditions": {
        "items": [
          {
            "items": [
              "minecraft:charcoal"
            ]
          }
        ]
      },
      "trigger": "minecraft:inventory_changed"
    },
    "has_mortar_and_pestle": {
      "conditions": {
        "items": [
          {
            "items": [
              "oldguns:mortar_and_pestle"
            ]
          }
        ]
      },
      "trigger": "minecraft:inventory_changed"
    },
    "has_saltpeter": {
      "conditions": {
        "items": [
          {
            "tag": "forge:dusts/saltpeter"
          }
        ]
      },
      "trigger": "minecraft:inventory_changed"
    },
    "has_sulfur": {
      "conditions": {
        "items": [
          {
            "tag": "forge:dusts/sulfur"
          }
        ]
      },
      "trigger": "minecraft:inventory_changed"
    },
    "has_the_recipe": {
      "conditions": {
        "recipe": "oldguns:rocket_powder"
      },
      "trigger": "minecraft:recipe_unlocked"
    }
  },
  "requirements": [
    [
      "has_saltpeter",
      "has_sulfur",
      "has_charcoal",
      "has_mortar_and_pestle",
      "has_the_recipe"
    ]
  ],
  "rewards": {
    "recipes": [
      "oldguns:rocket_powder"
    ]
  }
}